{"nodes": [{"id": "users_omidsalehi_desktop_ats_scratch_migrate_admission_dates_py", "label": "migrate_admission_dates.py", "file_type": "code", "source_file": "scratch/migrate_admission_dates.py", "source_location": "L1"}, {"id": "users_omidsalehi_desktop_ats_scratch_migrate_admission_dates_run", "label": "run()", "file_type": "code", "source_file": "scratch/migrate_admission_dates.py", "source_location": "L12", "_callable": true}], "edges": [{"source": "users_omidsalehi_desktop_ats_scratch_migrate_admission_dates_py", "target": "os", "relation": "imports", "context": "import", "confidence": "EXTRACTED", "source_file": "scratch/migrate_admission_dates.py", "source_location": "L1", "weight": 1.0}, {"source": "users_omidsalehi_desktop_ats_scratch_migrate_admission_dates_py", "target": "sys", "relation": "imports", "context": "import", "confidence": "EXTRACTED", "source_file": "scratch/migrate_admission_dates.py", "source_location": "L2", "weight": 1.0}, {"source": "users_omidsalehi_desktop_ats_scratch_migrate_admission_dates_py", "target": "django", "relation": "imports", "context": "import", "confidence": "EXTRACTED", "source_file": "scratch/migrate_admission_dates.py", "source_location": "L3", "weight": 1.0}, {"source": "users_omidsalehi_desktop_ats_scratch_migrate_admission_dates_py", "target": "django_db", "relation": "imports_from", "context": "import", "confidence": "EXTRACTED", "source_file": "scratch/migrate_admission_dates.py", "source_location": "L4", "weight": 1.0}, {"source": "users_omidsalehi_desktop_ats_scratch_migrate_admission_dates_py", "target": "apps_candidates_models", "relation": "imports_from", "context": "import", "confidence": "EXTRACTED", "source_file": "scratch/migrate_admission_dates.py", "source_location": "L10", "weight": 1.0}, {"source": "users_omidsalehi_desktop_ats_scratch_migrate_admission_dates_py", "target": "users_omidsalehi_desktop_ats_scratch_migrate_admission_dates_run", "relation": "contains", "confidence": "EXTRACTED", "source_file": "scratch/migrate_admission_dates.py", "source_location": "L12", "weight": 1.0}], "raw_calls": [{"caller_nid": "users_omidsalehi_desktop_ats_scratch_migrate_admission_dates_run", "callee": "atomic", "is_member_call": true, "source_file": "scratch/migrate_admission_dates.py", "source_location": "L13", "receiver": "transaction"}, {"caller_nid": "users_omidsalehi_desktop_ats_scratch_migrate_admission_dates_run", "callee": "count", "is_member_call": true, "source_file": "scratch/migrate_admission_dates.py", "source_location": "L15", "receiver": "selected_apps"}, {"caller_nid": "users_omidsalehi_desktop_ats_scratch_migrate_admission_dates_run", "callee": "save", "is_member_call": true, "source_file": "scratch/migrate_admission_dates.py", "source_location": "L23", "receiver": "app"}, {"caller_nid": "users_omidsalehi_desktop_ats_scratch_migrate_admission_dates_run", "callee": "save", "is_member_call": true, "source_file": "scratch/migrate_admission_dates.py", "source_location": "L27", "receiver": "app"}]}